["[\n  {\n    \"X\": 155,\n    \"Shop\": \"Glasses USA\",\n    \"LABLE\": \"30%\",\n    \"Desc\": \"30% off Sitewide at Glasses USA\",\n    \"Code\": \"DESIGNER30\",\n    \"Souce\": \"https://www.glassesusa.com/\",\n    \"LOGO\": \"/cnt/uploads/logos/glasses-usa.jpg?1606894191\",\n    \"Effective_date\": \"2022-08-24T09:01:00-07:00\",\n    \"Expire_date\": \"2022-12-20T03:59:00-08:00\",\n    \"img_link\": \"https://coupons.cnet.com/image/eyJrZXkiOiJjbnQvdXBsb2Fkcy9sb2dvcy8xLTgwMC1jb250YWN0cy5qcGciLCJvdXRwdXRGb3JtYXQiOiIiLCJlZGl0cyI6eyJyZXNpemUiOnsid2lkdGgiOjExNzB9fX0=?1606894191\"\n  },\n  {\n    \"X\": 276,\n    \"Shop\": \"Glasses USA\",\n    \"LABLE\": \"30%\",\n    \"Desc\": \"30% off Sitewide at Glasses USA\",\n    \"Code\": \"DESIGNER30\",\n    \"Souce\": \"https://www.glassesusa.com/\",\n    \"LOGO\": \"/cnt/uploads/logos/glasses-usa.jpg?1606894191\",\n    \"Effective_date\": \"2022-08-24T09:01:00-07:00\",\n    \"Expire_date\": \"2022-12-20T03:59:00-08:00\",\n    \"img_link\": \"https://coupons.cnet.com/image/eyJrZXkiOiJjbnQvdXBsb2Fkcy9sb2dvcy8zOWRvbGxhcmdsYXNzZXMuanBnIiwib3V0cHV0Rm9ybWF0IjoiIiwiZWRpdHMiOnsicmVzaXplIjp7IndpZHRoIjoxMTcwfX19?1606894191\"\n  },\n  {\n    \"X\": 2015,\n    \"Shop\": \"Glasses USA\",\n    \"LABLE\": \"30%\",\n    \"Desc\": \"30% off Sitewide at Glasses USA\",\n    \"Code\": \"DESIGNER30\",\n    \"Souce\": \"https://www.glassesusa.com/\",\n    \"LOGO\": \"/cnt/uploads/logos/glasses-usa.jpg?1606894191\",\n    \"Effective_date\": \"2022-08-24T09:01:00-07:00\",\n    \"Expire_date\": \"2022-12-20T03:59:00-08:00\",\n    \"img_link\": \"https://coupons.cnet.com/image/eyJrZXkiOiJjbnQvdXBsb2Fkcy9sb2dvcy9hYy1sZW5zLmpwZyIsIm91dHB1dEZvcm1hdCI6IiIsImVkaXRzIjp7InJlc2l6ZSI6eyJ3aWR0aCI6MTE3MH19fQ==?1606894191\"\n  },\n  {\n    \"X\": 6161,\n    \"Shop\": \"Glasses USA\",\n    \"LABLE\": \"30%\",\n    \"Desc\": \"30% off Sitewide at Glasses USA\",\n    \"Code\": \"DESIGNER30\",\n    \"Souce\": \"https://www.glassesusa.com/\",\n    \"LOGO\": \"/cnt/uploads/logos/glasses-usa.jpg?1606894191\",\n    \"Effective_date\": \"2022-08-24T09:01:00-07:00\",\n    \"Expire_date\": \"2022-12-20T03:59:00-08:00\",\n    \"img_link\": \"https://coupons.cnet.com/image/eyJrZXkiOiJjbnQvdXBsb2Fkcy9sb2dvcy9jb3N0YS1kZWwtbWFyLmpwZyIsIm91dHB1dEZvcm1hdCI6IiIsImVkaXRzIjp7InJlc2l6ZSI6eyJ3aWR0aCI6MTE3MH19fQ==?1620296106\"\n  },\n  {\n    \"X\": 6946,\n    \"Shop\": \"Glasses USA\",\n    \"LABLE\": \"30%\",\n    \"Desc\": \"30% off Sitewide at Glasses USA\",\n    \"Code\": \"DESIGNER30\",\n    \"Souce\": \"https://www.glassesusa.com/\",\n    \"LOGO\": \"/cnt/uploads/logos/glasses-usa.jpg?1606894191\",\n    \"Effective_date\": \"2022-08-24T09:01:00-07:00\",\n    \"Expire_date\": \"2022-12-20T03:59:00-08:00\",\n    \"img_link\": \"https://coupons.cnet.com/image/eyJrZXkiOiJjbnQvdXBsb2Fkcy9sb2dvcy9jb250YWN0c2RpcmVjdC5qcGciLCJvdXRwdXRGb3JtYXQiOiIiLCJlZGl0cyI6eyJyZXNpemUiOnsid2lkdGgiOjExNzB9fX0=?1606894191\"\n  },\n  {\n    \"X\": 7049,\n    \"Shop\": \"Glasses USA\",\n    \"LABLE\": \"30%\",\n    \"Desc\": \"30% off Sitewide at Glasses USA\",\n    \"Code\": \"DESIGNER30\",\n    \"Souce\": \"https://www.glassesusa.com/\",\n    \"LOGO\": \"/cnt/uploads/logos/glasses-usa.jpg?1606894191\",\n    \"Effective_date\": \"2022-08-24T09:01:00-07:00\",\n    \"Expire_date\": \"2022-12-20T03:59:00-08:00\",\n    \"img_link\": \"https://coupons.cnet.com/image/eyJrZXkiOiJjbnQvdXBsb2Fkcy9sb2dvcy9jb250YWN0LWxlbnMta2luZy5qcGciLCJvdXRwdXRGb3JtYXQiOiIiLCJlZGl0cyI6eyJyZXNpemUiOnsid2lkdGgiOjExNzB9fX0=?1606894191\"\n  },\n  {\n    \"X\": 8274,\n    \"Shop\": \"Glasses USA\",\n    \"LABLE\": \"30%\",\n    \"Desc\": \"30% off Sitewide at Glasses USA\",\n    \"Code\": \"DESIGNER30\",\n    \"Souce\": \"https://www.glassesusa.com/\",\n    \"LOGO\": \"/cnt/uploads/logos/glasses-usa.jpg?1606894191\",\n    \"Effective_date\": \"2022-08-24T09:01:00-07:00\",\n    \"Expire_date\": \"2022-12-20T03:59:00-08:00\",\n    \"img_link\": \"https://coupons.cnet.com/image/eyJrZXkiOiJjbnQvdXBsb2Fkcy9sb2dvcy9kaWZmLWV5ZXdlYXIuanBnIiwib3V0cHV0Rm9ybWF0IjoiIiwiZWRpdHMiOnsicmVzaXplIjp7IndpZHRoIjoxMTcwfX19?1606894191\"\n  },\n  {\n    \"X\": 8438,\n    \"Shop\": \"Glasses USA\",\n    \"LABLE\": \"30%\",\n    \"Desc\": \"30% off Sitewide at Glasses USA\",\n    \"Code\": \"DESIGNER30\",\n    \"Souce\": \"https://www.glassesusa.com/\",\n    \"LOGO\": \"/cnt/uploads/logos/glasses-usa.jpg?1606894191\",\n    \"Effective_date\": \"2022-08-24T09:01:00-07:00\",\n    \"Expire_date\": \"2022-12-20T03:59:00-08:00\",\n    \"img_link\": \"https://coupons.cnet.com/image/eyJrZXkiOiJjbnQvdXBsb2Fkcy9sb2dvcy9kaXNjb3VudC1jb250YWN0LWxlbnNlcy5qcGciLCJvdXRwdXRGb3JtYXQiOiIiLCJlZGl0cyI6eyJyZXNpemUiOnsid2lkdGgiOjExNzB9fX0=?1606894191\"\n  },\n  {\n    \"X\": 9581,\n    \"Shop\": \"Glasses USA\",\n    \"LABLE\": \"30%\",\n    \"Desc\": \"30% off Sitewide at Glasses USA\",\n    \"Code\": \"DESIGNER30\",\n    \"Souce\": \"https://www.glassesusa.com/\",\n    \"LOGO\": \"/cnt/uploads/logos/glasses-usa.jpg?1606894191\",\n    \"Effective_date\": \"2022-08-24T09:01:00-07:00\",\n    \"Expire_date\": \"2022-12-20T03:59:00-08:00\",\n    \"img_link\": \"https://coupons.cnet.com/image/eyJrZXkiOiJjbnQvdXBsb2Fkcy9sb2dvcy9leWVidXlkaXJlY3QuanBnIiwib3V0cHV0Rm9ybWF0IjoiIiwiZWRpdHMiOnsicmVzaXplIjp7IndpZHRoIjoxMTcwfX19?1606894191\"\n  },\n  {\n    \"X\": 11181,\n    \"Shop\": \"Glasses USA\",\n    \"LABLE\": \"30%\",\n    \"Desc\": \"30% off Sitewide at Glasses USA\",\n    \"Code\": \"DESIGNER30\",\n    \"Souce\": \"https://www.glassesusa.com/\",\n    \"LOGO\": \"/cnt/uploads/logos/glasses-usa.jpg?1606894191\",\n    \"Effective_date\": \"2022-08-24T09:01:00-07:00\",\n    \"Expire_date\": \"2022-12-20T03:59:00-08:00\",\n    \"img_link\": \"https://coupons.cnet.com/image/eyJrZXkiOiJjbnQvdXBsb2Fkcy9sb2dvcy9mcmFtZXMtZGlyZWN0LmpwZyIsIm91dHB1dEZvcm1hdCI6IiIsImVkaXRzIjp7InJlc2l6ZSI6eyJ3aWR0aCI6MTE3MH19fQ==?1606894191\"\n  },\n  {\n    \"X\": 11967,\n    \"Shop\": \"Glasses USA\",\n    \"LABLE\": \"$150\",\n    \"Desc\": \"Top Coupon: $150 off Multifocal Orders\",\n    \"Code\": \"multi150\",\n    \"Souce\": \"https://www.glassesusa.com/\",\n    \"LOGO\": \"/cnt/uploads/logos/glasses-usa.jpg?1606894191\",\n    \"Effective_date\": \"2019-11-26T13:18:00-08:00\",\n    \"check_date\": \"2021-10-25T00:10:35-07:00\",\n    \"img_link\": \"https://coupons.cnet.com/image/eyJrZXkiOiJjbnQvdXBsb2Fkcy9sb2dvcy9nbGFzc2VzLXVzYS5qcGciLCJvdXRwdXRGb3JtYXQiOiIiLCJlZGl0cyI6eyJyZXNpemUiOnsid2lkdGgiOjExNzB9fX0=?1606894191\"\n  },\n  {\n    \"X\": 11968,\n    \"Shop\": \"Glasses USA\",\n    \"LABLE\": \"30%\",\n    \"Desc\": \"30% off Sitewide at Glasses USA\",\n    \"Code\": \"DESIGNER30\",\n    \"Souce\": \"https://www.glassesusa.com/\",\n    \"LOGO\": \"/cnt/uploads/logos/glasses-usa.jpg?1606894191\",\n    \"Effective_date\": \"2022-08-24T09:01:00-07:00\",\n    \"Expire_date\": \"2022-12-20T03:59:00-08:00\",\n    \"img_link\": \"https://coupons.cnet.com/image/eyJrZXkiOiJjbnQvdXBsb2Fkcy9sb2dvcy9nbGFzc2VzLXVzYS5qcGciLCJvdXRwdXRGb3JtYXQiOiIiLCJlZGl0cyI6eyJyZXNpemUiOnsid2lkdGgiOjExNzB9fX0=?1606894191\"\n  },\n  {\n    \"X\": 11969,\n    \"Shop\": \"Glasses USA\",\n    \"LABLE\": \"25%\",\n    \"Desc\": \"25% off at Glasses USA\",\n    \"Code\": \"holiday55\",\n    \"Souce\": \"https://www.glassesusa.com/\",\n    \"LOGO\": \"/cnt/uploads/logos/glasses-usa.jpg?1606894191\",\n    \"Effective_date\": \"2019-04-08T17:28:00-07:00\",\n    \"check_date\": \"2020-12-11T00:28:50-08:00\",\n    \"img_link\": \"https://coupons.cnet.com/image/eyJrZXkiOiJjbnQvdXBsb2Fkcy9sb2dvcy9nbGFzc2VzLXVzYS5qcGciLCJvdXRwdXRGb3JtYXQiOiIiLCJlZGl0cyI6eyJyZXNpemUiOnsid2lkdGgiOjExNzB9fX0=?1606894191\"\n  },\n  {\n    \"X\": 11970,\n    \"Shop\": \"Glasses USA\",\n    \"LABLE\": \"25%\",\n    \"Desc\": \"25% off at Glasses USA\",\n    \"Code\": \"25OFF\",\n    \"Souce\": \"https://www.glassesusa.com/\",\n    \"LOGO\": \"/cnt/uploads/logos/glasses-usa.jpg?1606894191\",\n    \"Effective_date\": \"2020-09-10T11:31:00-07:00\",\n    \"check_date\": \"2020-12-11T00:28:12-08:00\",\n    \"img_link\": \"https://coupons.cnet.com/image/eyJrZXkiOiJjbnQvdXBsb2Fkcy9sb2dvcy9nbGFzc2VzLXVzYS5qcGciLCJvdXRwdXRGb3JtYXQiOiIiLCJlZGl0cyI6eyJyZXNpemUiOnsid2lkdGgiOjExNzB9fX0=?1606894191\"\n  },\n  {\n    \"X\": 11971,\n    \"Shop\": \"Glasses USA\",\n    \"LABLE\": \"10%\",\n    \"Desc\": \"Claim 10% off with this Promo Code!\",\n    \"Code\": \"VIP10-HGY76-2504GH\",\n    \"Souce\": \"https://www.glassesusa.com/\",\n    \"LOGO\": \"/cnt/uploads/logos/glasses-usa.jpg?1606894191\",\n    \"Effective_date\": \"2018-09-05T15:29:00-07:00\",\n    \"check_date\": \"2022-05-11T05:44:42-07:00\",\n    \"img_link\": \"https://coupons.cnet.com/image/eyJrZXkiOiJjbnQvdXBsb2Fkcy9sb2dvcy9nbGFzc2VzLXVzYS5qcGciLCJvdXRwdXRGb3JtYXQiOiIiLCJlZGl0cyI6eyJyZXNpemUiOnsid2lkdGgiOjExNzB9fX0=?1606894191\"\n  },\n  {\n    \"X\": 11972,\n    \"Shop\": \"Glasses USA\",\n    \"LABLE\": \"$10\",\n    \"Desc\": \"$10 off Your Order with Glasses USA Promo Code\",\n    \"Code\": \"XTRA10\",\n    \"Souce\": \"https://www.glassesusa.com/\",\n    \"LOGO\": \"/cnt/uploads/logos/glasses-usa.jpg?1606894191\",\n    \"Effective_date\": \"2020-10-28T11:25:00-07:00\",\n    \"check_date\": \"2021-01-28T00:09:42-08:00\",\n    \"Expire_date\": \"2022-12-23T04:59:00-08:00\",\n    \"img_link\": \"https://coupons.cnet.com/image/eyJrZXkiOiJjbnQvdXBsb2Fkcy9sb2dvcy9nbGFzc2VzLXVzYS5qcGciLCJvdXRwdXRGb3JtYXQiOiIiLCJlZGl0cyI6eyJyZXNpemUiOnsid2lkdGgiOjExNzB9fX0=?1606894191\"\n  },\n  {\n    \"X\": 11973,\n    \"Shop\": \"Glasses USA\",\n    \"LABLE\": \"$125\",\n    \"Desc\": \"$125 off Multifocals plus Free Shipping with Glasses USA Promo Code\",\n    \"Code\": \"MULTI125\",\n    \"Souce\": \"https://www.glassesusa.com/\",\n    \"LOGO\": \"/cnt/uploads/logos/glasses-usa.jpg?1606894191\",\n    \"Effective_date\": \"2022-07-29T03:33:00-07:00\",\n    \"img_link\": \"https://coupons.cnet.com/image/eyJrZXkiOiJjbnQvdXBsb2Fkcy9sb2dvcy9nbGFzc2VzLXVzYS5qcGciLCJvdXRwdXRGb3JtYXQiOiIiLCJlZGl0cyI6eyJyZXNpemUiOnsid2lkdGgiOjExNzB9fX0=?1606894191\"\n  },\n  {\n    \"X\": 11974,\n    \"Shop\": \"Glasses USA\",\n    \"LABLE\": \"$75\",\n    \"Desc\": \"Glasses USA Promo Code: $75 off Multifocals\",\n    \"Code\": \"multi75\",\n    \"Souce\": \"https://www.glassesusa.com/\",\n    \"LOGO\": \"/cnt/uploads/logos/glasses-usa.jpg?1606894191\",\n    \"Effective_date\": \"2019-11-26T13:15:00-08:00\",\n    \"check_date\": \"2021-10-19T00:06:41-07:00\",\n    \"Expire_date\": \"2022-12-20T00:06:00-08:00\",\n    \"img_link\": \"https://coupons.cnet.com/image/eyJrZXkiOiJjbnQvdXBsb2Fkcy9sb2dvcy9nbGFzc2VzLXVzYS5qcGciLCJvdXRwdXRGb3JtYXQiOiIiLCJlZGl0cyI6eyJyZXNpemUiOnsid2lkdGgiOjExNzB9fX0=?1606894191\"\n  },\n  {\n    \"X\": 11975,\n    \"Shop\": \"Glasses USA\",\n    \"LABLE\": \"$75\",\n    \"Desc\": \"Top Coupon: $75 off plus Free Shipping\",\n    \"Code\": \"MULTI75\",\n    \"Souce\": \"https://www.glassesusa.com/\",\n    \"LOGO\": \"/cnt/uploads/logos/glasses-usa.jpg?1606894191\",\n    \"Effective_date\": \"2022-07-29T03:34:00-07:00\",\n    \"img_link\": \"https://coupons.cnet.com/image/eyJrZXkiOiJjbnQvdXBsb2Fkcy9sb2dvcy9nbGFzc2VzLXVzYS5qcGciLCJvdXRwdXRGb3JtYXQiOiIiLCJlZGl0cyI6eyJyZXNpemUiOnsid2lkdGgiOjExNzB9fX0=?1606894191\"\n  },\n  {\n    \"X\": 11976,\n    \"Shop\": \"Glasses USA\",\n    \"LABLE\": \"65%\",\n    \"Desc\": \"Grab 65% off Frames with RX Lenses plus Free Shipping\",\n    \"Code\": \"CYBER65\",\n    \"Souce\": \"https://www.glassesusa.com/\",\n    \"LOGO\": \"/cnt/uploads/logos/glasses-usa.jpg?1606894191\",\n    \"Effective_date\": \"2019-12-02T00:00:00-08:00\",\n    \"check_date\": \"2019-12-02T09:01:37-08:00\",\n    \"Expire_date\": \"2022-12-20T23:59:59-08:00\",\n    \"img_link\": \"https://coupons.cnet.com/image/eyJrZXkiOiJjbnQvdXBsb2Fkcy9sb2dvcy9nbGFzc2VzLXVzYS5qcGciLCJvdXRwdXRGb3JtYXQiOiIiLCJlZGl0cyI6eyJyZXNpemUiOnsid2lkdGgiOjExNzB9fX0=?1606894191\"\n  },\n  {\n    \"X\": 11977,\n    \"Shop\": \"Glasses USA\",\n    \"LABLE\": \"65%\",\n    \"Desc\": \"Grab 65% off with Newsletter Sign-Up\",\n    \"Code\": \"Sign Up for Glasses USA Email Newsletter\",\n    \"Souce\": \"https://www.glassesusa.com/\",\n    \"LOGO\": \"/cnt/uploads/logos/glasses-usa.jpg?1606894191\",\n    \"Effective_date\": \"2015-06-12T05:08:00-07:00\",\n    \"check_date\": \"2020-03-20T00:18:00-07:00\",\n    \"Expire_date\": \"2023-12-31T23:59:00-08:00\",\n    \"img_link\": \"https://coupons.cnet.com/image/eyJrZXkiOiJjbnQvdXBsb2Fkcy9sb2dvcy9nbGFzc2VzLXVzYS5qcGciLCJvdXRwdXRGb3JtYXQiOiIiLCJlZGl0cyI6eyJyZXNpemUiOnsid2lkdGgiOjExNzB9fX0=?1606894191\"\n  },\n  {\n    \"X\": 11978,\n    \"Shop\": \"Glasses USA\",\n    \"LABLE\": \"60%\",\n    \"Desc\": \"Glasses USA Promo Code: 60% off Frames\",\n    \"Code\": \"BLUE60\",\n    \"Souce\": \"https://www.glassesusa.com/\",\n    \"LOGO\": \"/cnt/uploads/logos/glasses-usa.jpg?1606894191\",\n    \"Effective_date\": \"2022-04-27T19:30:00-07:00\",\n    \"check_date\": \"2022-04-28T04:53:07-07:00\",\n    \"img_link\": \"https://coupons.cnet.com/image/eyJrZXkiOiJjbnQvdXBsb2Fkcy9sb2dvcy9nbGFzc2VzLXVzYS5qcGciLCJvdXRwdXRGb3JtYXQiOiIiLCJlZGl0cyI6eyJyZXNpemUiOnsid2lkdGgiOjExNzB9fX0=?1606894191\"\n  },\n  {\n    \"X\": 11979,\n    \"Shop\": \"Glasses USA\",\n    \"LABLE\": \"60%\",\n    \"Desc\": \"60% off Lens Upgrades at Glasses USA\",\n    \"Code\": \"LENSES60\",\n    \"Souce\": \"https://www.glassesusa.com/\",\n    \"LOGO\": \"/cnt/uploads/logos/glasses-usa.jpg?1606894191\",\n    \"Effective_date\": \"2020-07-21T00:38:00-07:00\",\n    \"check_date\": \"2021-03-08T00:52:04-08:00\",\n    \"img_link\": \"https://coupons.cnet.com/image/eyJrZXkiOiJjbnQvdXBsb2Fkcy9sb2dvcy9nbGFzc2VzLXVzYS5qcGciLCJvdXRwdXRGb3JtYXQiOiIiLCJlZGl0cyI6eyJyZXNpemUiOnsid2lkdGgiOjExNzB9fX0=?1606894191\"\n  },\n  {\n    \"X\": 11980,\n    \"Shop\": \"Glasses USA\",\n    \"LABLE\": \"60%\",\n    \"Desc\": \"Glasses USA Promo Code: 60% off Black Frames + Free Shipping\",\n    \"Code\": \"offers60b\",\n    \"Souce\": \"https://www.glassesusa.com/\",\n    \"LOGO\": \"/cnt/uploads/logos/glasses-usa.jpg?1606894191\",\n    \"Effective_date\": \"2017-04-18T17:45:00-07:00\",\n    \"check_date\": \"2017-04-19T07:17:55-07:00\",\n    \"img_link\": \"https://coupons.cnet.com/image/eyJrZXkiOiJjbnQvdXBsb2Fkcy9sb2dvcy9nbGFzc2VzLXVzYS5qcGciLCJvdXRwdXRGb3JtYXQiOiIiLCJlZGl0cyI6eyJyZXNpemUiOnsid2lkdGgiOjExNzB9fX0=?1606894191\"\n  },\n  {\n    \"X\": 11981,\n    \"Shop\": \"Glasses USA\",\n    \"LABLE\": \"60%\",\n    \"Desc\": \"Glasses USA Promo Code: 60% off plus Free Shipping\",\n    \"Code\": \"VIP60-JBQT-2408\",\n    \"Souce\": \"https://www.glassesusa.com/\",\n    \"LOGO\": \"/cnt/uploads/logos/glasses-usa.jpg?1606894191\",\n    \"Effective_date\": \"2016-11-21T23:23:00-08:00\",\n    \"check_date\": \"2021-01-21T00:24:05-08:00\",\n    \"img_link\": \"https://coupons.cnet.com/image/eyJrZXkiOiJjbnQvdXBsb2Fkcy9sb2dvcy9nbGFzc2VzLXVzYS5qcGciLCJvdXRwdXRGb3JtYXQiOiIiLCJlZGl0cyI6eyJyZXNpemUiOnsid2lkdGgiOjExNzB9fX0=?1606894191\"\n  },\n  {\n    \"X\": 11982,\n    \"Shop\": \"Glasses USA\",\n    \"LABLE\": \"50%\",\n    \"Desc\": \"Save Big: 50% off Tortoise Shell Collection\",\n    \"Code\": \"tort50\",\n    \"Souce\": \"https://www.glassesusa.com/\",\n    \"LOGO\": \"/cnt/uploads/logos/glasses-usa.jpg?1606894191\",\n    \"Effective_date\": \"2019-05-24T23:35:00-07:00\",\n    \"check_date\": \"2020-04-11T00:26:46-07:00\",\n    \"img_link\": \"https://coupons.cnet.com/image/eyJrZXkiOiJjbnQvdXBsb2Fkcy9sb2dvcy9nbGFzc2VzLXVzYS5qcGciLCJvdXRwdXRGb3JtYXQiOiIiLCJlZGl0cyI6eyJyZXNpemUiOnsid2lkdGgiOjExNzB9fX0=?1606894191\"\n  },\n  {\n    \"X\": 11983,\n    \"Shop\": \"Glasses USA\",\n    \"LABLE\": \"50%\",\n    \"Desc\": \"50% off on Eyeglasses and Sunglasses at Glasses USA\",\n    \"Code\": \"COZY50\",\n    \"Souce\": \"https://www.glassesusa.com/\",\n    \"LOGO\": \"/cnt/uploads/logos/glasses-usa.jpg?1606894191\",\n    \"Effective_date\": \"2022-12-05T15:54:00-08:00\",\n    \"Expire_date\": \"2022-12-25T04:59:00-08:00\",\n    \"img_link\": \"https://coupons.cnet.com/image/eyJrZXkiOiJjbnQvdXBsb2Fkcy9sb2dvcy9nbGFzc2VzLXVzYS5qcGciLCJvdXRwdXRGb3JtYXQiOiIiLCJlZGl0cyI6eyJyZXNpemUiOnsid2lkdGgiOjExNzB9fX0=?1606894191\"\n  },\n  {\n    \"X\": 11984,\n    \"Shop\": \"Glasses USA\",\n    \"LABLE\": \"50%\",\n    \"Desc\": \"50% off Frames plus Free Shipping at Glasses USA\",\n    \"Code\": \"SPRING50\",\n    \"Souce\": \"https://www.glassesusa.com/\",\n    \"LOGO\": \"/cnt/uploads/logos/glasses-usa.jpg?1606894191\",\n    \"Effective_date\": \"2022-07-29T03:28:00-07:00\",\n    \"img_link\": \"https://coupons.cnet.com/image/eyJrZXkiOiJjbnQvdXBsb2Fkcy9sb2dvcy9nbGFzc2VzLXVzYS5qcGciLCJvdXRwdXRGb3JtYXQiOiIiLCJlZGl0cyI6eyJyZXNpemUiOnsid2lkdGgiOjExNzB9fX0=?1606894191\"\n  },\n  {\n    \"X\": 11985,\n    \"Shop\": \"Glasses USA\",\n    \"LABLE\": \"50%\",\n    \"Desc\": \"Glasses USA Promo Code: 50% off First Pair of Glasses\",\n    \"Code\": \"WELCOME50\",\n    \"Souce\": \"https://www.glassesusa.com/\",\n    \"LOGO\": \"/cnt/uploads/logos/glasses-usa.jpg?1606894191\",\n    \"Effective_date\": \"2019-03-09T22:01:00-08:00\",\n    \"check_date\": \"2020-06-13T00:54:22-07:00\",\n    \"img_link\": \"https://coupons.cnet.com/image/eyJrZXkiOiJjbnQvdXBsb2Fkcy9sb2dvcy9nbGFzc2VzLXVzYS5qcGciLCJvdXRwdXRGb3JtYXQiOiIiLCJlZGl0cyI6eyJyZXNpemUiOnsid2lkdGgiOjExNzB9fX0=?1606894191\"\n  },\n  {\n    \"X\": 11986,\n    \"Shop\": \"Glasses USA\",\n    \"LABLE\": \"$50\",\n    \"Desc\": \"Top Coupon: $50 off plus Free Shipping\",\n    \"Code\": \"MULTI50\",\n    \"Souce\": \"https://www.glassesusa.com/\",\n    \"LOGO\": \"/cnt/uploads/logos/glasses-usa.jpg?1606894191\",\n    \"Effective_date\": \"2018-10-12T14:22:00-07:00\",\n    \"check_date\": \"2018-10-12T23:37:02-07:00\",\n    \"Expire_date\": \"2022-12-23T23:37:00-08:00\",\n    \"img_link\": \"https://coupons.cnet.com/image/eyJrZXkiOiJjbnQvdXBsb2Fkcy9sb2dvcy9nbGFzc2VzLXVzYS5qcGciLCJvdXRwdXRGb3JtYXQiOiIiLCJlZGl0cyI6eyJyZXNpemUiOnsid2lkdGgiOjExNzB9fX0=?1606894191\"\n  },\n  {\n    \"X\": 11987,\n    \"Shop\": \"Glasses USA\",\n    \"LABLE\": \"$50\",\n    \"Desc\": \"$50 off plus Free Shipping at Glasses USA\",\n    \"Code\": \"SAVE50\",\n    \"Souce\": \"https://www.glassesusa.com/\",\n    \"LOGO\": \"/cnt/uploads/logos/glasses-usa.jpg?1606894191\",\n    \"Effective_date\": \"2022-07-29T03:27:00-07:00\",\n    \"img_link\": \"https://coupons.cnet.com/image/eyJrZXkiOiJjbnQvdXBsb2Fkcy9sb2dvcy9nbGFzc2VzLXVzYS5qcGciLCJvdXRwdXRGb3JtYXQiOiIiLCJlZGl0cyI6eyJyZXNpemUiOnsid2lkdGgiOjExNzB9fX0=?1606894191\"\n  },\n  {\n    \"X\": 11988,\n    \"Shop\": \"Glasses USA\",\n    \"LABLE\": \"$50\",\n    \"Desc\": \"Glasses USA Promo Code: $50 off plus Free Shipping\",\n    \"Code\": \"save50\",\n    \"Souce\": \"https://www.glassesusa.com/\",\n    \"LOGO\": \"/cnt/uploads/logos/glasses-usa.jpg?1606894191\",\n    \"Effective_date\": \"2018-05-20T06:28:00-07:00\",\n    \"check_date\": \"2022-05-09T20:14:33-07:00\",\n    \"Expire_date\": \"2022-12-21T03:59:00-08:00\",\n    \"img_link\": \"https://coupons.cnet.com/image/eyJrZXkiOiJjbnQvdXBsb2Fkcy9sb2dvcy9nbGFzc2VzLXVzYS5qcGciLCJvdXRwdXRGb3JtYXQiOiIiLCJlZGl0cyI6eyJyZXNpemUiOnsid2lkdGgiOjExNzB9fX0=?1606894191\"\n  },\n  {\n    \"X\": 11989,\n    \"Shop\": \"Glasses USA\",\n    \"LABLE\": \"$50\",\n    \"Desc\": \"$50 off Progressive and Bifocal Lenses with Glasses USA Promo Code\",\n    \"Code\": \"MULTI50\",\n    \"Souce\": \"https://www.glassesusa.com/\",\n    \"LOGO\": \"/cnt/uploads/logos/glasses-usa.jpg?1606894191\",\n    \"Effective_date\": \"2020-04-22T01:29:00-07:00\",\n    \"check_date\": \"2020-06-07T01:00:29-07:00\",\n    \"img_link\": \"https://coupons.cnet.com/image/eyJrZXkiOiJjbnQvdXBsb2Fkcy9sb2dvcy9nbGFzc2VzLXVzYS5qcGciLCJvdXRwdXRGb3JtYXQiOiIiLCJlZGl0cyI6eyJyZXNpemUiOnsid2lkdGgiOjExNzB9fX0=?1606894191\"\n  },\n  {\n    \"X\": 11990,\n    \"Shop\": \"Glasses USA\",\n    \"LABLE\": \"40%\",\n    \"Desc\": \"Save Big: 40% off plus Free Shipping\",\n    \"Code\": \"ENTIRE40\",\n    \"Souce\": \"https://www.glassesusa.com/\",\n    \"LOGO\": \"/cnt/uploads/logos/glasses-usa.jpg?1606894191\",\n    \"Effective_date\": \"2022-07-29T03:27:00-07:00\",\n    \"img_link\": \"https://coupons.cnet.com/image/eyJrZXkiOiJjbnQvdXBsb2Fkcy9sb2dvcy9nbGFzc2VzLXVzYS5qcGciLCJvdXRwdXRGb3JtYXQiOiIiLCJlZGl0cyI6eyJyZXNpemUiOnsid2lkdGgiOjExNzB9fX0=?1606894191\"\n  },\n  {\n    \"X\": 11991,\n    \"Shop\": \"Glasses USA\",\n    \"LABLE\": \"30%\",\n    \"Desc\": \"Grab 30% off Multifocal Sale\",\n    \"Code\": \"multi150\",\n    \"Souce\": \"https://www.glassesusa.com/\",\n    \"LOGO\": \"/cnt/uploads/logos/glasses-usa.jpg?1606894191\",\n    \"Effective_date\": \"2019-07-28T21:12:00-07:00\",\n    \"check_date\": \"2019-11-12T00:11:23-08:00\",\n    \"Expire_date\": \"2022-12-16T04:59:00-08:00\",\n    \"img_link\": \"https://coupons.cnet.com/image/eyJrZXkiOiJjbnQvdXBsb2Fkcy9sb2dvcy9nbGFzc2VzLXVzYS5qcGciLCJvdXRwdXRGb3JtYXQiOiIiLCJlZGl0cyI6eyJyZXNpemUiOnsid2lkdGgiOjExNzB9fX0=?1606894191\"\n  },\n  {\n    \"X\": 11992,\n    \"Shop\": \"Glasses USA\",\n    \"LABLE\": \"25%\",\n    \"Desc\": \"Claim 25% off Lenses with this Promo Code!\",\n    \"Code\": \"LENSES25\",\n    \"Souce\": \"https://www.glassesusa.com/\",\n    \"LOGO\": \"/cnt/uploads/logos/glasses-usa.jpg?1606894191\",\n    \"Effective_date\": \"2020-04-22T01:36:00-07:00\",\n    \"check_date\": \"2022-04-27T00:32:29-07:00\",\n    \"img_link\": \"https://coupons.cnet.com/image/eyJrZXkiOiJjbnQvdXBsb2Fkcy9sb2dvcy9nbGFzc2VzLXVzYS5qcGciLCJvdXRwdXRGb3JtYXQiOiIiLCJlZGl0cyI6eyJyZXNpemUiOnsid2lkdGgiOjExNzB9fX0=?1606894191\"\n  },\n  {\n    \"X\": 11993,\n    \"Shop\": \"Glasses USA\",\n    \"LABLE\": \"25%\",\n    \"Desc\": \"Grab 25% off Contact Lenses\",\n    \"Code\": \"CONTACTS25\",\n    \"Souce\": \"https://www.glassesusa.com/\",\n    \"LOGO\": \"/cnt/uploads/logos/glasses-usa.jpg?1606894191\",\n    \"Effective_date\": \"2019-08-29T15:11:00-07:00\",\n    \"check_date\": \"2022-01-04T00:45:13-08:00\",\n    \"img_link\": \"https://coupons.cnet.com/image/eyJrZXkiOiJjbnQvdXBsb2Fkcy9sb2dvcy9nbGFzc2VzLXVzYS5qcGciLCJvdXRwdXRGb3JtYXQiOiIiLCJlZGl0cyI6eyJyZXNpemUiOnsid2lkdGgiOjExNzB9fX0=?1606894191\"\n  },\n  {\n    \"X\": 11994,\n    \"Shop\": \"Glasses USA\",\n    \"LABLE\": \"$25\",\n    \"Desc\": \"Glasses USA Promo Code: $25 off Multifocals plus Free Shipping\",\n    \"Code\": \"MULTI25\",\n    \"Souce\": \"https://www.glassesusa.com/\",\n    \"LOGO\": \"/cnt/uploads/logos/glasses-usa.jpg?1606894191\",\n    \"Effective_date\": \"2022-07-29T03:31:00-07:00\",\n    \"img_link\": \"https://coupons.cnet.com/image/eyJrZXkiOiJjbnQvdXBsb2Fkcy9sb2dvcy9nbGFzc2VzLXVzYS5qcGciLCJvdXRwdXRGb3JtYXQiOiIiLCJlZGl0cyI6eyJyZXNpemUiOnsid2lkdGgiOjExNzB9fX0=?1606894191\"\n  },\n  {\n    \"X\": 11995,\n    \"Shop\": \"Glasses USA\",\n    \"LABLE\": \"$10\",\n    \"Desc\": \"$10 off on Sunglasses at Glasses USA\",\n    \"Code\": \"SUNNIES10\",\n    \"Souce\": \"https://www.glassesusa.com/\",\n    \"LOGO\": \"/cnt/uploads/logos/glasses-usa.jpg?1606894191\",\n    \"Effective_date\": \"2022-07-29T03:30:00-07:00\",\n    \"img_link\": \"https://coupons.cnet.com/image/eyJrZXkiOiJjbnQvdXBsb2Fkcy9sb2dvcy9nbGFzc2VzLXVzYS5qcGciLCJvdXRwdXRGb3JtYXQiOiIiLCJlZGl0cyI6eyJyZXNpemUiOnsid2lkdGgiOjExNzB9fX0=?1606894191\"\n  },\n  {\n    \"X\": 11996,\n    \"Shop\": \"Glasses USA\",\n    \"Desc\": \"Buy 1 Get 1 Free at Glasses USA\",\n    \"Code\": \"BOGOFREE\",\n    \"Souce\": \"https://www.glassesusa.com/\",\n    \"LOGO\": \"/cnt/uploads/logos/glasses-usa.jpg?1606894191\",\n    \"Effective_date\": \"2022-04-27T19:30:00-07:00\",\n    \"check_date\": \"2022-04-28T04:55:42-07:00\",\n    \"Expire_date\": \"2022-12-16T04:59:00-08:00\",\n    \"img_link\": \"https://coupons.cnet.com/image/eyJrZXkiOiJjbnQvdXBsb2Fkcy9sb2dvcy9nbGFzc2VzLXVzYS5qcGciLCJvdXRwdXRGb3JtYXQiOiIiLCJlZGl0cyI6eyJyZXNpemUiOnsid2lkdGgiOjExNzB9fX0=?1606894191\"\n  },\n  {\n    \"X\": 11997,\n    \"Shop\": \"Glasses USA\",\n    \"LABLE\": \"70%\",\n    \"Desc\": \"Up to 70% off at Glasses USA\",\n    \"Code\": \"LENSE70\",\n    \"Souce\": \"https://www.glassesusa.com/\",\n    \"LOGO\": \"/cnt/uploads/logos/glasses-usa.jpg?1606894191\",\n    \"Effective_date\": \"2019-01-18T20:59:00-08:00\",\n    \"check_date\": \"2021-03-09T00:56:38-08:00\",\n    \"img_link\": \"https://coupons.cnet.com/image/eyJrZXkiOiJjbnQvdXBsb2Fkcy9sb2dvcy9nbGFzc2VzLXVzYS5qcGciLCJvdXRwdXRGb3JtYXQiOiIiLCJlZGl0cyI6eyJyZXNpemUiOnsid2lkdGgiOjExNzB9fX0=?1606894191\"\n  },\n  {\n    \"X\": 11998,\n    \"Shop\": \"Glasses USA\",\n    \"LABLE\": \"65%\",\n    \"Desc\": \"Glasses USA Coupon: Up to 65% off Frames\",\n    \"Code\": \"WELCOME65\",\n    \"Souce\": \"https://www.glassesusa.com/\",\n    \"LOGO\": \"/cnt/uploads/logos/glasses-usa.jpg?1606894191\",\n    \"Effective_date\": \"2022-05-22T07:03:00-07:00\",\n    \"check_date\": \"2022-05-22T16:13:42-07:00\",\n    \"Expire_date\": \"2022-12-25T03:59:00-08:00\",\n    \"img_link\": \"https://coupons.cnet.com/image/eyJrZXkiOiJjbnQvdXBsb2Fkcy9sb2dvcy9nbGFzc2VzLXVzYS5qcGciLCJvdXRwdXRGb3JtYXQiOiIiLCJlZGl0cyI6eyJyZXNpemUiOnsid2lkdGgiOjExNzB9fX0=?1606894191\"\n  },\n  {\n    \"X\": 11999,\n    \"Shop\": \"Glasses USA\",\n    \"LABLE\": \"$25\",\n    \"Desc\": \"Use this Glasses USA Offer: $25 off all Orders\",\n    \"Code\": \"Discount Displayed on Site\",\n    \"Souce\": \"https://www.glassesusa.com/\",\n    \"LOGO\": \"/cnt/uploads/logos/glasses-usa.jpg?1606894191\",\n    \"Effective_date\": \"2022-07-30T10:53:00-07:00\",\n    \"img_link\": \"https://coupons.cnet.com/image/eyJrZXkiOiJjbnQvdXBsb2Fkcy9sb2dvcy9nbGFzc2VzLXVzYS5qcGciLCJvdXRwdXRGb3JtYXQiOiIiLCJlZGl0cyI6eyJyZXNpemUiOnsid2lkdGgiOjExNzB9fX0=?1606894191\"\n  },\n  {\n    \"X\": 12000,\n    \"Shop\": \"Glasses USA\",\n    \"Desc\": \"Final Sale! Get Free Shipping with this Offer\",\n    \"Code\": \"Discount Displayed on Site\",\n    \"Souce\": \"https://www.glassesusa.com/\",\n    \"LOGO\": \"/cnt/uploads/logos/glasses-usa.jpg?1606894191\",\n    \"Effective_date\": \"2022-07-30T10:54:00-07:00\",\n    \"img_link\": \"https://coupons.cnet.com/image/eyJrZXkiOiJjbnQvdXBsb2Fkcy9sb2dvcy9nbGFzc2VzLXVzYS5qcGciLCJvdXRwdXRGb3JtYXQiOiIiLCJlZGl0cyI6eyJyZXNpemUiOnsid2lkdGgiOjExNzB9fX0=?1606894191\"\n  },\n  {\n    \"X\": 12001,\n    \"Shop\": \"Glasses USA\",\n    \"LABLE\": \"$150\",\n    \"Desc\": \"$150 off all Purchases at Glasses USA\",\n    \"Code\": \"HOL150\",\n    \"Souce\": \"https://www.glassesusa.com/\",\n    \"LOGO\": \"/cnt/uploads/logos/glasses-usa.jpg?1606894191\",\n    \"Effective_date\": \"2016-12-15T05:07:00-08:00\",\n    \"check_date\": \"2016-12-15T14:27:23-08:00\",\n    \"Expire_date\": \"2016-12-15T14:27:23-08:00\",\n    \"img_link\": \"https://coupons.cnet.com/image/eyJrZXkiOiJjbnQvdXBsb2Fkcy9sb2dvcy9nbGFzc2VzLXVzYS5qcGciLCJvdXRwdXRGb3JtYXQiOiIiLCJlZGl0cyI6eyJyZXNpemUiOnsid2lkdGgiOjExNzB9fX0=?1606894191\"\n  },\n  {\n    \"X\": 12002,\n    \"Shop\": \"Glasses USA\",\n    \"LABLE\": \"$150\",\n    \"Desc\": \"$150 off at Glasses USA\",\n    \"Code\": \"MULTI150\",\n    \"Souce\": \"https://www.glassesusa.com/\",\n    \"LOGO\": \"/cnt/uploads/logos/glasses-usa.jpg?1606894191\",\n    \"Effective_date\": \"2019-03-06T16:20:00-08:00\",\n    \"check_date\": \"2019-06-07T00:06:00-07:00\",\n    \"Expire_date\": \"2019-06-07T00:06:00-07:00\",\n    \"img_link\": \"https://coupons.cnet.com/image/eyJrZXkiOiJjbnQvdXBsb2Fkcy9sb2dvcy9nbGFzc2VzLXVzYS5qcGciLCJvdXRwdXRGb3JtYXQiOiIiLCJlZGl0cyI6eyJyZXNpemUiOnsid2lkdGgiOjExNzB9fX0=?1606894191\"\n  },\n  {\n    \"X\": 12003,\n    \"Shop\": \"Glasses USA\",\n    \"LABLE\": \"55%\",\n    \"Desc\": \"55% off on Frames at Glasses USA\",\n    \"Code\": \"SAVEBIG55\",\n    \"Souce\": \"https://www.glassesusa.com/\",\n    \"LOGO\": \"/cnt/uploads/logos/glasses-usa.jpg?1606894191\",\n    \"Effective_date\": \"2022-11-20T18:28:00-08:00\",\n    \"Expire_date\": \"2022-12-02T04:59:00-08:00\",\n    \"img_link\": \"https://coupons.cnet.com/image/eyJrZXkiOiJjbnQvdXBsb2Fkcy9sb2dvcy9nbGFzc2VzLXVzYS5qcGciLCJvdXRwdXRGb3JtYXQiOiIiLCJlZGl0cyI6eyJyZXNpemUiOnsid2lkdGgiOjExNzB9fX0=?1606894191\"\n  },\n  {\n    \"X\": 12004,\n    \"Shop\": \"Glasses USA\",\n    \"LABLE\": \"25%\",\n    \"Desc\": \"Save at Glasses USA with Up to 25% Off Lenses\",\n    \"Code\": \"LENSES25\",\n    \"Souce\": \"https://www.glassesusa.com/\",\n    \"LOGO\": \"/cnt/uploads/logos/glasses-usa.jpg?1606894191\",\n    \"Effective_date\": \"2022-10-25T02:55:00-07:00\",\n    \"Expire_date\": \"2022-12-01T03:59:00-08:00\",\n    \"img_link\": \"https://coupons.cnet.com/image/eyJrZXkiOiJjbnQvdXBsb2Fkcy9sb2dvcy9nbGFzc2VzLXVzYS5qcGciLCJvdXRwdXRGb3JtYXQiOiIiLCJlZGl0cyI6eyJyZXNpemUiOnsid2lkdGgiOjExNzB9fX0=?1606894191\"\n  },\n  {\n    \"X\": 12005,\n    \"Shop\": \"Glasses USA\",\n    \"LABLE\": \"$125\",\n    \"Desc\": \"$125 off Multifocal Glasses with Glasses USA Promo Code\",\n    \"Code\": \"MULTI125\",\n    \"Souce\": \"https://www.glassesusa.com/\",\n    \"LOGO\": \"/cnt/uploads/logos/glasses-usa.jpg?1606894191\",\n    \"Effective_date\": \"2020-04-22T01:19:00-07:00\",\n    \"check_date\": \"2021-10-25T00:09:58-07:00\",\n    \"Expire_date\": \"2022-12-01T00:09:00-08:00\",\n    \"img_link\": \"https://coupons.cnet.com/image/eyJrZXkiOiJjbnQvdXBsb2Fkcy9sb2dvcy9nbGFzc2VzLXVzYS5qcGciLCJvdXRwdXRGb3JtYXQiOiIiLCJlZGl0cyI6eyJyZXNpemUiOnsid2lkdGgiOjExNzB9fX0=?1606894191\"\n  },\n  {\n    \"X\": 12006,\n    \"Shop\": \"Glasses USA\",\n    \"LABLE\": \"$25\",\n    \"Desc\": \"$25 off with Glasses USA Promo Code\",\n    \"Code\": \"save25\",\n    \"Souce\": \"https://www.glassesusa.com/\",\n    \"LOGO\": \"/cnt/uploads/logos/glasses-usa.jpg?1606894191\",\n    \"Effective_date\": \"2022-11-09T00:01:00-08:00\",\n    \"check_date\": \"2022-06-02T18:15:37-07:00\",\n    \"Expire_date\": \"2022-11-30T23:59:59-08:00\",\n    \"img_link\": \"https://coupons.cnet.com/image/eyJrZXkiOiJjbnQvdXBsb2Fkcy9sb2dvcy9nbGFzc2VzLXVzYS5qcGciLCJvdXRwdXRGb3JtYXQiOiIiLCJlZGl0cyI6eyJyZXNpemUiOnsid2lkdGgiOjExNzB9fX0=?1606894191\"\n  },\n  {\n    \"X\": 12007,\n    \"Shop\": \"Glasses USA\",\n    \"LABLE\": \"65%\",\n    \"Desc\": \"65% off Frames at Glasses USA\",\n    \"Code\": \"black65\",\n    \"Souce\": \"https://www.glassesusa.com/\",\n    \"LOGO\": \"/cnt/uploads/logos/glasses-usa.jpg?1606894191\",\n    \"Effective_date\": \"2018-11-22T13:53:00-08:00\",\n    \"check_date\": \"2021-01-09T01:18:02-08:00\",\n    \"Expire_date\": \"2022-11-29T04:59:00-08:00\",\n    \"img_link\": \"https://coupons.cnet.com/image/eyJrZXkiOiJjbnQvdXBsb2Fkcy9sb2dvcy9nbGFzc2VzLXVzYS5qcGciLCJvdXRwdXRGb3JtYXQiOiIiLCJlZGl0cyI6eyJyZXNpemUiOnsid2lkdGgiOjExNzB9fX0=?1606894191\"\n  },\n  {\n    \"X\": 12008,\n    \"Shop\": \"Glasses USA\",\n    \"Desc\": \"Glasses USA Coupon: Buy 1 Get 1 Free Prescription Glasses\",\n    \"Code\": \"BLACKBOGO\",\n    \"Souce\": \"https://www.glassesusa.com/\",\n    \"LOGO\": \"/cnt/uploads/logos/glasses-usa.jpg?1606894191\",\n    \"Effective_date\": \"2022-11-27T22:02:00-08:00\",\n    \"Expire_date\": \"2022-11-29T04:59:00-08:00\",\n    \"img_link\": \"https://coupons.cnet.com/image/eyJrZXkiOiJjbnQvdXBsb2Fkcy9sb2dvcy9nbGFzc2VzLXVzYS5qcGciLCJvdXRwdXRGb3JtYXQiOiIiLCJlZGl0cyI6eyJyZXNpemUiOnsid2lkdGgiOjExNzB9fX0=?1606894191\"\n  },\n  {\n    \"X\": 12009,\n    \"Shop\": \"Glasses USA\",\n    \"LABLE\": \"25%\",\n    \"Desc\": \"Glasses USA Promo Code: 25% off Frames\",\n    \"Code\": \"VIP10-HGY76-2504GH\",\n    \"Souce\": \"https://www.glassesusa.com/\",\n    \"LOGO\": \"/cnt/uploads/logos/glasses-usa.jpg?1606894191\",\n    \"Effective_date\": \"2022-10-24T04:16:00-07:00\",\n    \"Expire_date\": \"2022-11-25T04:59:00-08:00\",\n    \"img_link\": \"https://coupons.cnet.com/image/eyJrZXkiOiJjbnQvdXBsb2Fkcy9sb2dvcy9nbGFzc2VzLXVzYS5qcGciLCJvdXRwdXRGb3JtYXQiOiIiLCJlZGl0cyI6eyJyZXNpemUiOnsid2lkdGgiOjExNzB9fX0=?1606894191\"\n  },\n  {\n    \"X\": 12010,\n    \"Shop\": \"Glasses USA\",\n    \"LABLE\": \"20%\",\n    \"Desc\": \"Save Big: 20% off Lenses\",\n    \"Code\": \"LENSES50\",\n    \"Souce\": \"https://www.glassesusa.com/\",\n    \"LOGO\": \"/cnt/uploads/logos/glasses-usa.jpg?1606894191\",\n    \"Effective_date\": \"2022-10-22T05:28:00-07:00\",\n    \"Expire_date\": \"2022-11-25T04:59:00-08:00\",\n    \"img_link\": \"https://coupons.cnet.com/image/eyJrZXkiOiJjbnQvdXBsb2Fkcy9sb2dvcy9nbGFzc2VzLXVzYS5qcGciLCJvdXRwdXRGb3JtYXQiOiIiLCJlZGl0cyI6eyJyZXNpemUiOnsid2lkdGgiOjExNzB9fX0=?1606894191\"\n  },\n  {\n    \"X\": 12011,\n    \"Shop\": \"Glasses USA\",\n    \"LABLE\": \"$10\",\n    \"Desc\": \"$10 off Sunglasses with Glasses USA Promo Code\",\n    \"Code\": \"SUN10\",\n    \"Souce\": \"https://www.glassesusa.com/\",\n    \"LOGO\": \"/cnt/uploads/logos/glasses-usa.jpg?1606894191\",\n    \"Effective_date\": \"2022-04-27T19:31:00-07:00\",\n    \"check_date\": \"2022-04-28T04:52:28-07:00\",\n    \"Expire_date\": \"2022-11-23T03:59:00-08:00\",\n    \"img_link\": \"https://coupons.cnet.com/image/eyJrZXkiOiJjbnQvdXBsb2Fkcy9sb2dvcy9nbGFzc2VzLXVzYS5qcGciLCJvdXRwdXRGb3JtYXQiOiIiLCJlZGl0cyI6eyJyZXNpemUiOnsid2lkdGgiOjExNzB9fX0=?1606894191\"\n  },\n  {\n    \"X\": 12012,\n    \"Shop\": \"Glasses USA\",\n    \"LABLE\": \"$10\",\n    \"Desc\": \"$10 off plus Free Shipping with Glasses USA Promo Code\",\n    \"Code\": \"PERK10\",\n    \"Souce\": \"https://www.glassesusa.com/\",\n    \"LOGO\": \"/cnt/uploads/logos/glasses-usa.jpg?1606894191\",\n    \"Effective_date\": \"2022-04-27T19:32:00-07:00\",\n    \"check_date\": \"2022-04-28T04:52:06-07:00\",\n    \"Expire_date\": \"2022-11-19T04:59:00-08:00\",\n    \"img_link\": \"https://coupons.cnet.com/image/eyJrZXkiOiJjbnQvdXBsb2Fkcy9sb2dvcy9nbGFzc2VzLXVzYS5qcGciLCJvdXRwdXRGb3JtYXQiOiIiLCJlZGl0cyI6eyJyZXNpemUiOnsid2lkdGgiOjExNzB9fX0=?1606894191\"\n  },\n  {\n    \"X\": 12013,\n    \"Shop\": \"Glasses USA\",\n    \"LABLE\": \"10%\",\n    \"Desc\": \"Grab 10% off all Orders\",\n    \"Code\": \"EXPRESS\",\n    \"Souce\": \"https://www.glassesusa.com/\",\n    \"LOGO\": \"/cnt/uploads/logos/glasses-usa.jpg?1606894191\",\n    \"Effective_date\": \"2022-05-03T18:16:00-07:00\",\n    \"check_date\": \"2022-05-05T19:32:01-07:00\",\n    \"Expire_date\": \"2022-11-19T04:59:00-08:00\",\n    \"img_link\": \"https://coupons.cnet.com/image/eyJrZXkiOiJjbnQvdXBsb2Fkcy9sb2dvcy9nbGFzc2VzLXVzYS5qcGciLCJvdXRwdXRGb3JtYXQiOiIiLCJlZGl0cyI6eyJyZXNpemUiOnsid2lkdGgiOjExNzB9fX0=?1606894191\"\n  },\n  {\n    \"X\": 12014,\n    \"Shop\": \"Glasses USA\",\n    \"LABLE\": \"60%\",\n    \"Desc\": \"Save Big: 60% off Eyeglasses and Sunglasses\",\n    \"Code\": \"EARLY60\",\n    \"Souce\": \"https://www.glassesusa.com/\",\n    \"LOGO\": \"/cnt/uploads/logos/glasses-usa.jpg?1606894191\",\n    \"Effective_date\": \"2022-10-13T19:35:00-07:00\",\n    \"Expire_date\": \"2022-11-11T04:59:00-08:00\",\n    \"img_link\": \"https://coupons.cnet.com/image/eyJrZXkiOiJjbnQvdXBsb2Fkcy9sb2dvcy9nbGFzc2VzLXVzYS5qcGciLCJvdXRwdXRGb3JtYXQiOiIiLCJlZGl0cyI6eyJyZXNpemUiOnsid2lkdGgiOjExNzB9fX0=?1606894191\"\n  },\n  {\n    \"X\": 12015,\n    \"Shop\": \"Glasses USA\",\n    \"LABLE\": \"$50\",\n    \"Desc\": \"Up to $50 off at Glasses USA\",\n    \"Code\": \"DESIGNER40\",\n    \"Souce\": \"https://www.glassesusa.com/\",\n    \"LOGO\": \"/cnt/uploads/logos/glasses-usa.jpg?1606894191\",\n    \"Effective_date\": \"2022-10-21T15:50:00-07:00\",\n    \"Expire_date\": \"2022-11-11T03:59:00-08:00\",\n    \"img_link\": \"https://coupons.cnet.com/image/eyJrZXkiOiJjbnQvdXBsb2Fkcy9sb2dvcy9nbGFzc2VzLXVzYS5qcGciLCJvdXRwdXRGb3JtYXQiOiIiLCJlZGl0cyI6eyJyZXNpemUiOnsid2lkdGgiOjExNzB9fX0=?1606894191\"\n  },\n  {\n    \"X\": 17436,\n    \"Shop\": \"Glasses USA\",\n    \"LABLE\": \"30%\",\n    \"Desc\": \"30% off Sitewide at Glasses USA\",\n    \"Code\": \"DESIGNER30\",\n    \"Souce\": \"https://www.glassesusa.com/\",\n    \"LOGO\": \"/cnt/uploads/logos/glasses-usa.jpg?1606894191\",\n    \"Effective_date\": \"2022-08-24T09:01:00-07:00\",\n    \"Expire_date\": \"2022-12-20T03:59:00-08:00\",\n    \"img_link\": \"https://coupons.cnet.com/image/eyJrZXkiOiJjbnQvdXBsb2Fkcy9sb2dvcy9sZW5zLWNvbS5qcGciLCJvdXRwdXRGb3JtYXQiOiIiLCJlZGl0cyI6eyJyZXNpemUiOnsid2lkdGgiOjExNzB9fX0=?1606894191\"\n  },\n  {\n    \"X\": 21024,\n    \"Shop\": \"Glasses USA\",\n    \"LABLE\": \"30%\",\n    \"Desc\": \"30% off Sitewide at Glasses USA\",\n    \"Code\": \"DESIGNER30\",\n    \"Souce\": \"https://www.glassesusa.com/\",\n    \"LOGO\": \"/cnt/uploads/logos/glasses-usa.jpg?1606894191\",\n    \"Effective_date\": \"2022-08-24T09:01:00-07:00\",\n    \"Expire_date\": \"2022-12-20T03:59:00-08:00\",\n    \"img_link\": \"https://coupons.cnet.com/image/eyJrZXkiOiJjbnQvdXBsb2Fkcy9sb2dvcy9vYWtsZXkuanBnIiwib3V0cHV0Rm9ybWF0IjoiIiwiZWRpdHMiOnsicmVzaXplIjp7IndpZHRoIjoxMTcwfX19?1606894191\"\n  },\n  {\n    \"X\": 23007,\n    \"Shop\": \"Glasses USA\",\n    \"LABLE\": \"30%\",\n    \"Desc\": \"30% off Sitewide at Glasses USA\",\n    \"Code\": \"DESIGNER30\",\n    \"Souce\": \"https://www.glassesusa.com/\",\n    \"LOGO\": \"/cnt/uploads/logos/glasses-usa.jpg?1606894191\",\n    \"Effective_date\": \"2022-08-24T09:01:00-07:00\",\n    \"Expire_date\": \"2022-12-20T03:59:00-08:00\",\n    \"img_link\": \"https://coupons.cnet.com/image/eyJrZXkiOiJjbnQvdXBsb2Fkcy9sb2dvcy9wYWlyLWV5ZXdlYXIuanBnIiwib3V0cHV0Rm9ybWF0IjoiIiwiZWRpdHMiOnsicmVzaXplIjp7IndpZHRoIjoxMTcwfX19?1651658408\"\n  },\n  {\n    \"X\": 23467,\n    \"Shop\": \"Glasses USA\",\n    \"LABLE\": \"30%\",\n    \"Desc\": \"30% off Sitewide at Glasses USA\",\n    \"Code\": \"DESIGNER30\",\n    \"Souce\": \"https://www.glassesusa.com/\",\n    \"LOGO\": \"/cnt/uploads/logos/glasses-usa.jpg?1606894191\",\n    \"Effective_date\": \"2022-08-24T09:01:00-07:00\",\n    \"Expire_date\": \"2022-12-20T03:59:00-08:00\",\n    \"img_link\": \"https://coupons.cnet.com/image/eyJrZXkiOiJjbnQvdXBsb2Fkcy9sb2dvcy9yYXktYmFuLmpwZyIsIm91dHB1dEZvcm1hdCI6IiIsImVkaXRzIjp7InJlc2l6ZSI6eyJ3aWR0aCI6MTE3MH19fQ==?1606894191\"\n  },\n  {\n    \"X\": 25045,\n    \"Shop\": \"Glasses USA\",\n    \"LABLE\": \"30%\",\n    \"Desc\": \"30% off Sitewide at Glasses USA\",\n    \"Code\": \"DESIGNER30\",\n    \"Souce\": \"https://www.glassesusa.com/\",\n    \"LOGO\": \"/cnt/uploads/logos/glasses-usa.jpg?1606894191\",\n    \"Effective_date\": \"2022-08-24T09:01:00-07:00\",\n    \"Expire_date\": \"2022-12-20T03:59:00-08:00\",\n    \"img_link\": \"https://coupons.cnet.com/image/eyJrZXkiOiJjbnQvdXBsb2Fkcy9sb2dvcy9zbWFydGJ1eWdsYXNzZXMuanBnIiwib3V0cHV0Rm9ybWF0IjoiIiwiZWRpdHMiOnsicmVzaXplIjp7IndpZHRoIjoxMTcwfX19?1606894191\"\n  },\n  {\n    \"X\": 31104,\n    \"Shop\": \"Glasses USA\",\n    \"LABLE\": \"30%\",\n    \"Desc\": \"30% off Sitewide at Glasses USA\",\n    \"Code\": \"DESIGNER30\",\n    \"Souce\": \"https://www.glassesusa.com/\",\n    \"LOGO\": \"/cnt/uploads/logos/glasses-usa.jpg?1606894191\",\n    \"Effective_date\": \"2022-08-24T09:01:00-07:00\",\n    \"Expire_date\": \"2022-12-20T03:59:00-08:00\",\n    \"img_link\": \"https://coupons.cnet.com/image/eyJrZXkiOiJjbnQvdXBsb2Fkcy9sb2dvcy93ZWJleWVjYXJlLmpwZyIsIm91dHB1dEZvcm1hdCI6IiIsImVkaXRzIjp7InJlc2l6ZSI6eyJ3aWR0aCI6MTE3MH19fQ==?1606894191\"\n  },\n  {\n    \"X\": 31197,\n    \"Shop\": \"Glasses USA\",\n    \"LABLE\": \"30%\",\n    \"Desc\": \"30% off Sitewide at Glasses USA\",\n    \"Code\": \"DESIGNER30\",\n    \"Souce\": \"https://www.glassesusa.com/\",\n    \"LOGO\": \"/cnt/uploads/logos/glasses-usa.jpg?1606894191\",\n    \"Effective_date\": \"2022-08-24T09:01:00-07:00\",\n    \"Expire_date\": \"2022-12-20T03:59:00-08:00\",\n    \"img_link\": \"https://coupons.cnet.com/image/eyJrZXkiOiJjbnQvdXBsb2Fkcy9sb2dvcy93YXJieS1wYXJrZXIuanBnIiwib3V0cHV0Rm9ybWF0IjoiIiwiZWRpdHMiOnsicmVzaXplIjp7IndpZHRoIjoxMTcwfX19?1606894191\"\n  },\n  {\n    \"X\": 31674,\n    \"Shop\": \"Glasses USA\",\n    \"LABLE\": \"30%\",\n    \"Desc\": \"30% off Sitewide at Glasses USA\",\n    \"Code\": \"DESIGNER30\",\n    \"Souce\": \"https://www.glassesusa.com/\",\n    \"LOGO\": \"/cnt/uploads/logos/glasses-usa.jpg?1606894191\",\n    \"Effective_date\": \"2022-08-24T09:01:00-07:00\",\n    \"Expire_date\": \"2022-12-20T03:59:00-08:00\",\n    \"img_link\": \"https://coupons.cnet.com/image/eyJrZXkiOiJjbnQvdXBsb2Fkcy9sb2dvcy95ZXNnbGFzc2VzLmpwZyIsIm91dHB1dEZvcm1hdCI6IiIsImVkaXRzIjp7InJlc2l6ZSI6eyJ3aWR0aCI6MTE3MH19fQ==?1669119308\"\n  },\n  {\n    \"X\": 31719,\n    \"Shop\": \"Glasses USA\",\n    \"LABLE\": \"30%\",\n    \"Desc\": \"30% off Sitewide at Glasses USA\",\n    \"Code\": \"DESIGNER30\",\n    \"Souce\": \"https://www.glassesusa.com/\",\n    \"LOGO\": \"/cnt/uploads/logos/glasses-usa.jpg?1606894191\",\n    \"Effective_date\": \"2022-08-24T09:01:00-07:00\",\n    \"Expire_date\": \"2022-12-20T03:59:00-08:00\",\n    \"img_link\": \"https://coupons.cnet.com/image/eyJrZXkiOiJjbnQvdXBsb2Fkcy9sb2dvcy96ZW5uaS1vcHRpY2FsLmpwZyIsIm91dHB1dEZvcm1hdCI6IiIsImVkaXRzIjp7InJlc2l6ZSI6eyJ3aWR0aCI6MTE3MH19fQ==?1606894191\"\n  }\n]"]
