["[\n  {\n    \"X\": 16019,\n    \"Shop\": \"Jos A Bank\",\n    \"LABLE\": \"50%\",\n    \"Desc\": \"Seasonal Savings: Buy 1 Get 1 Half Off Jeans\",\n    \"Code\": \"Discount Applied at Checkout\",\n    \"Souce\": \"https://www.josbank.com/\",\n    \"LOGO\": \"/cnt/uploads/logos/jos-a-bank.jpg?1606894191\",\n    \"Effective_date\": \"2022-09-23T04:46:00-07:00\",\n    \"img_link\": \"https://coupons.cnet.com/image/eyJrZXkiOiJjbnQvdXBsb2Fkcy9sb2dvcy9qb3MtYS1iYW5rLmpwZyIsIm91dHB1dEZvcm1hdCI6IiIsImVkaXRzIjp7InJlc2l6ZSI6eyJ3aWR0aCI6MTE3MH19fQ==?1606894191\"\n  },\n  {\n    \"X\": 16020,\n    \"Shop\": \"Jos A Bank\",\n    \"LABLE\": \"$25\",\n    \"Desc\": \"Jos A Bank Promo Code: $25 off Sitewide\",\n    \"Code\": \"AZFA1010101\",\n    \"Souce\": \"https://www.josbank.com/\",\n    \"LOGO\": \"/cnt/uploads/logos/jos-a-bank.jpg?1606894191\",\n    \"Effective_date\": \"2022-04-28T03:27:00-07:00\",\n    \"check_date\": \"2022-12-09T00:52:47-08:00\",\n    \"img_link\": \"https://coupons.cnet.com/image/eyJrZXkiOiJjbnQvdXBsb2Fkcy9sb2dvcy9qb3MtYS1iYW5rLmpwZyIsIm91dHB1dEZvcm1hdCI6IiIsImVkaXRzIjp7InJlc2l6ZSI6eyJ3aWR0aCI6MTE3MH19fQ==?1606894191\"\n  },\n  {\n    \"X\": 16021,\n    \"Shop\": \"Jos A Bank\",\n    \"LABLE\": \"$25\",\n    \"Desc\": \"$25 off all Purchases at Jos A Bank\",\n    \"Code\": \"AZEY2951812\",\n    \"Souce\": \"https://www.josbank.com/\",\n    \"LOGO\": \"/cnt/uploads/logos/jos-a-bank.jpg?1606894191\",\n    \"Effective_date\": \"2022-11-25T00:11:00-08:00\",\n    \"check_date\": \"2022-12-01T11:38:19-08:00\",\n    \"img_link\": \"https://coupons.cnet.com/image/eyJrZXkiOiJjbnQvdXBsb2Fkcy9sb2dvcy9qb3MtYS1iYW5rLmpwZyIsIm91dHB1dEZvcm1hdCI6IiIsImVkaXRzIjp7InJlc2l6ZSI6eyJ3aWR0aCI6MTE3MH19fQ==?1606894191\"\n  },\n  {\n    \"X\": 16022,\n    \"Shop\": \"Jos A Bank\",\n    \"LABLE\": \"$25\",\n    \"Desc\": \"$25 off with Text Alert Sign Up at Jos A Bank\",\n    \"Code\": \"Text JAB25 to 70188 to Receive Discount\",\n    \"Souce\": \"https://www.josbank.com/\",\n    \"LOGO\": \"/cnt/uploads/logos/jos-a-bank.jpg?1606894191\",\n    \"Effective_date\": \"2021-09-17T07:47:00-07:00\",\n    \"check_date\": \"2021-09-17T16:55:27-07:00\",\n    \"Expire_date\": \"2023-12-31T23:59:00-08:00\",\n    \"img_link\": \"https://coupons.cnet.com/image/eyJrZXkiOiJjbnQvdXBsb2Fkcy9sb2dvcy9qb3MtYS1iYW5rLmpwZyIsIm91dHB1dEZvcm1hdCI6IiIsImVkaXRzIjp7InJlc2l6ZSI6eyJ3aWR0aCI6MTE3MH19fQ==?1606894191\"\n  },\n  {\n    \"X\": 16023,\n    \"Shop\": \"Jos A Bank\",\n    \"LABLE\": \"10%\",\n    \"Desc\": \"10% off Reserve Collection Blazer at Jos A Bank\",\n    \"Code\": \"AXMF1189720\",\n    \"Souce\": \"https://www.josbank.com/\",\n    \"LOGO\": \"/cnt/uploads/logos/jos-a-bank.jpg?1606894191\",\n    \"Effective_date\": \"2022-08-31T00:33:00-07:00\",\n    \"img_link\": \"https://coupons.cnet.com/image/eyJrZXkiOiJjbnQvdXBsb2Fkcy9sb2dvcy9qb3MtYS1iYW5rLmpwZyIsIm91dHB1dEZvcm1hdCI6IiIsImVkaXRzIjp7InJlc2l6ZSI6eyJ3aWR0aCI6MTE3MH19fQ==?1606894191\"\n  },\n  {\n    \"X\": 16024,\n    \"Shop\": \"Jos A Bank\",\n    \"Desc\": \"Save at Jos A Bank - Free Shipping\",\n    \"Code\": \"Discount Applied at Checkout\",\n    \"Souce\": \"https://www.josbank.com/\",\n    \"LOGO\": \"/cnt/uploads/logos/jos-a-bank.jpg?1606894191\",\n    \"Effective_date\": \"2020-04-24T07:06:00-07:00\",\n    \"check_date\": \"2022-05-11T13:05:21-07:00\",\n    \"img_link\": \"https://coupons.cnet.com/image/eyJrZXkiOiJjbnQvdXBsb2Fkcy9sb2dvcy9qb3MtYS1iYW5rLmpwZyIsIm91dHB1dEZvcm1hdCI6IiIsImVkaXRzIjp7InJlc2l6ZSI6eyJ3aWR0aCI6MTE3MH19fQ==?1606894191\"\n  },\n  {\n    \"X\": 16025,\n    \"Shop\": \"Jos A Bank\",\n    \"LABLE\": \"50%\",\n    \"Desc\": \"Don't miss this Deal at Jos A Bank for Buy 1 Get 1 Half Off Casual Pants\",\n    \"Code\": \"Discount Applied at Checkout\",\n    \"Souce\": \"https://www.josbank.com/\",\n    \"LOGO\": \"/cnt/uploads/logos/jos-a-bank.jpg?1606894191\",\n    \"Effective_date\": \"2022-09-23T04:47:00-07:00\",\n    \"img_link\": \"https://coupons.cnet.com/image/eyJrZXkiOiJjbnQvdXBsb2Fkcy9sb2dvcy9qb3MtYS1iYW5rLmpwZyIsIm91dHB1dEZvcm1hdCI6IiIsImVkaXRzIjp7InJlc2l6ZSI6eyJ3aWR0aCI6MTE3MH19fQ==?1606894191\"\n  },\n  {\n    \"X\": 16026,\n    \"Shop\": \"Jos A Bank\",\n    \"LABLE\": \"50%\",\n    \"Desc\": \"Take advantage: Buy 1 Get 1 Half Off Accessories and Fragrances\",\n    \"Code\": \"Discount Applied at Checkout\",\n    \"Souce\": \"https://www.josbank.com/\",\n    \"LOGO\": \"/cnt/uploads/logos/jos-a-bank.jpg?1606894191\",\n    \"Effective_date\": \"2022-09-23T04:47:00-07:00\",\n    \"img_link\": \"https://coupons.cnet.com/image/eyJrZXkiOiJjbnQvdXBsb2Fkcy9sb2dvcy9qb3MtYS1iYW5rLmpwZyIsIm91dHB1dEZvcm1hdCI6IiIsImVkaXRzIjp7InJlc2l6ZSI6eyJ3aWR0aCI6MTE3MH19fQ==?1606894191\"\n  },\n  {\n    \"X\": 16027,\n    \"Shop\": \"Jos A Bank\",\n    \"LABLE\": \"50%\",\n    \"Desc\": \"Final Sale! Get Buy 1 Get 1 Half Off Shoes with this Offer\",\n    \"Code\": \"Discount Applied at Checkout\",\n    \"Souce\": \"https://www.josbank.com/\",\n    \"LOGO\": \"/cnt/uploads/logos/jos-a-bank.jpg?1606894191\",\n    \"Effective_date\": \"2022-09-23T04:47:00-07:00\",\n    \"img_link\": \"https://coupons.cnet.com/image/eyJrZXkiOiJjbnQvdXBsb2Fkcy9sb2dvcy9qb3MtYS1iYW5rLmpwZyIsIm91dHB1dEZvcm1hdCI6IiIsImVkaXRzIjp7InJlc2l6ZSI6eyJ3aWR0aCI6MTE3MH19fQ==?1606894191\"\n  },\n  {\n    \"X\": 16028,\n    \"Shop\": \"Jos A Bank\",\n    \"LABLE\": \"50%\",\n    \"Desc\": \"Jos A Bank Offer - Buy 1 Get 1 Half Off Dress Pants\",\n    \"Code\": \"Discount Applied at Checkout\",\n    \"Souce\": \"https://www.josbank.com/\",\n    \"LOGO\": \"/cnt/uploads/logos/jos-a-bank.jpg?1606894191\",\n    \"Effective_date\": \"2022-09-23T04:48:00-07:00\",\n    \"img_link\": \"https://coupons.cnet.com/image/eyJrZXkiOiJjbnQvdXBsb2Fkcy9sb2dvcy9qb3MtYS1iYW5rLmpwZyIsIm91dHB1dEZvcm1hdCI6IiIsImVkaXRzIjp7InJlc2l6ZSI6eyJ3aWR0aCI6MTE3MH19fQ==?1606894191\"\n  },\n  {\n    \"X\": 16029,\n    \"Shop\": \"Jos A Bank\",\n    \"LABLE\": \"$39.99\",\n    \"Desc\": \"Save at Jos A Bank - Select Shorts Now $39.99\",\n    \"Code\": \"Discount Displayed on Site\",\n    \"Souce\": \"https://www.josbank.com/\",\n    \"LOGO\": \"/cnt/uploads/logos/jos-a-bank.jpg?1606894191\",\n    \"Effective_date\": \"2022-08-12T23:08:00-07:00\",\n    \"img_link\": \"https://coupons.cnet.com/image/eyJrZXkiOiJjbnQvdXBsb2Fkcy9sb2dvcy9qb3MtYS1iYW5rLmpwZyIsIm91dHB1dEZvcm1hdCI6IiIsImVkaXRzIjp7InJlc2l6ZSI6eyJ3aWR0aCI6MTE3MH19fQ==?1606894191\"\n  },\n  {\n    \"X\": 16030,\n    \"Shop\": \"Jos A Bank\",\n    \"LABLE\": \"$39.99\",\n    \"Desc\": \"Don't miss this Deal at Jos A Bank for Denim Jackets Now $39.99\",\n    \"Code\": \"Discount Displayed on Site\",\n    \"Souce\": \"https://www.josbank.com/\",\n    \"LOGO\": \"/cnt/uploads/logos/jos-a-bank.jpg?1606894191\",\n    \"Effective_date\": \"2022-08-12T23:10:00-07:00\",\n    \"img_link\": \"https://coupons.cnet.com/image/eyJrZXkiOiJjbnQvdXBsb2Fkcy9sb2dvcy9qb3MtYS1iYW5rLmpwZyIsIm91dHB1dEZvcm1hdCI6IiIsImVkaXRzIjp7InJlc2l6ZSI6eyJ3aWR0aCI6MTE3MH19fQ==?1606894191\"\n  },\n  {\n    \"X\": 16031,\n    \"Shop\": \"Jos A Bank\",\n    \"LABLE\": \"70%\",\n    \"Desc\": \"Jos A Bank Offer - Up to 70% off Sale items\",\n    \"Code\": \"Discount Displayed on Site\",\n    \"Souce\": \"https://www.josbank.com/\",\n    \"LOGO\": \"/cnt/uploads/logos/jos-a-bank.jpg?1606894191\",\n    \"Effective_date\": \"2022-08-12T23:11:00-07:00\",\n    \"img_link\": \"https://coupons.cnet.com/image/eyJrZXkiOiJjbnQvdXBsb2Fkcy9sb2dvcy9qb3MtYS1iYW5rLmpwZyIsIm91dHB1dEZvcm1hdCI6IiIsImVkaXRzIjp7InJlc2l6ZSI6eyJ3aWR0aCI6MTE3MH19fQ==?1606894191\"\n  },\n  {\n    \"X\": 16032,\n    \"Shop\": \"Jos A Bank\",\n    \"LABLE\": \"60%\",\n    \"Desc\": \"Claim 60% off Your Order with this Promo Code!\",\n    \"Code\": \"TODAY\",\n    \"Souce\": \"https://www.josbank.com/\",\n    \"LOGO\": \"/cnt/uploads/logos/jos-a-bank.jpg?1606894191\",\n    \"Effective_date\": \"2015-06-17T23:56:00-07:00\",\n    \"check_date\": \"2015-06-28T21:50:59-07:00\",\n    \"Expire_date\": \"2015-06-24T23:59:59-07:00\",\n    \"img_link\": \"https://coupons.cnet.com/image/eyJrZXkiOiJjbnQvdXBsb2Fkcy9sb2dvcy9qb3MtYS1iYW5rLmpwZyIsIm91dHB1dEZvcm1hdCI6IiIsImVkaXRzIjp7InJlc2l6ZSI6eyJ3aWR0aCI6MTE3MH19fQ==?1606894191\"\n  },\n  {\n    \"X\": 16033,\n    \"Shop\": \"Jos A Bank\",\n    \"LABLE\": \"55%\",\n    \"Desc\": \"Grab 55% off Sitewide\",\n    \"Code\": \"FRIEND55\",\n    \"Souce\": \"https://www.josbank.com/\",\n    \"LOGO\": \"/cnt/uploads/logos/jos-a-bank.jpg?1606894191\",\n    \"Effective_date\": \"2018-04-30T04:52:00-07:00\",\n    \"check_date\": \"2018-04-30T14:02:17-07:00\",\n    \"Expire_date\": \"2018-05-02T23:59:59-07:00\",\n    \"img_link\": \"https://coupons.cnet.com/image/eyJrZXkiOiJjbnQvdXBsb2Fkcy9sb2dvcy9qb3MtYS1iYW5rLmpwZyIsIm91dHB1dEZvcm1hdCI6IiIsImVkaXRzIjp7InJlc2l6ZSI6eyJ3aWR0aCI6MTE3MH19fQ==?1606894191\"\n  },\n  {\n    \"X\": 16034,\n    \"Shop\": \"Jos A Bank\",\n    \"LABLE\": \"$25\",\n    \"Desc\": \"Top Coupon: $25 off Sitewide\",\n    \"Code\": \"AZEY3381866\",\n    \"Souce\": \"https://www.josbank.com/\",\n    \"LOGO\": \"/cnt/uploads/logos/jos-a-bank.jpg?1606894191\",\n    \"Effective_date\": \"2022-11-29T16:22:00-08:00\",\n    \"check_date\": \"2022-12-05T05:19:13-08:00\",\n    \"Expire_date\": \"2022-12-07T04:59:00-08:00\",\n    \"img_link\": \"https://coupons.cnet.com/image/eyJrZXkiOiJjbnQvdXBsb2Fkcy9sb2dvcy9qb3MtYS1iYW5rLmpwZyIsIm91dHB1dEZvcm1hdCI6IiIsImVkaXRzIjp7InJlc2l6ZSI6eyJ3aWR0aCI6MTE3MH19fQ==?1606894191\"\n  },\n  {\n    \"X\": 16035,\n    \"Shop\": \"Jos A Bank\",\n    \"LABLE\": \"$25\",\n    \"Desc\": \"$25 off Sitewide at Jos A Bank\",\n    \"Code\": \"AZEY2638883\",\n    \"Souce\": \"https://www.josbank.com/\",\n    \"LOGO\": \"/cnt/uploads/logos/jos-a-bank.jpg?1606894191\",\n    \"Effective_date\": \"2022-11-16T18:25:00-08:00\",\n    \"check_date\": \"2022-11-22T11:11:30-08:00\",\n    \"Expire_date\": \"2022-12-07T04:59:00-08:00\",\n    \"img_link\": \"https://coupons.cnet.com/image/eyJrZXkiOiJjbnQvdXBsb2Fkcy9sb2dvcy9qb3MtYS1iYW5rLmpwZyIsIm91dHB1dEZvcm1hdCI6IiIsImVkaXRzIjp7InJlc2l6ZSI6eyJ3aWR0aCI6MTE3MH19fQ==?1606894191\"\n  },\n  {\n    \"X\": 16036,\n    \"Shop\": \"Jos A Bank\",\n    \"LABLE\": \"$25\",\n    \"Desc\": \"$25 off with Text Alert Sign Up with Jos A Bank Promo Code\",\n    \"Code\": \"Sign Up for Text Alerts to Receive Discount\",\n    \"Souce\": \"https://www.josbank.com/\",\n    \"LOGO\": \"/cnt/uploads/logos/jos-a-bank.jpg?1606894191\",\n    \"Effective_date\": \"2022-10-25T15:24:00-07:00\",\n    \"check_date\": \"2022-11-18T12:26:31-08:00\",\n    \"Expire_date\": \"2022-12-02T04:59:00-08:00\",\n    \"img_link\": \"https://coupons.cnet.com/image/eyJrZXkiOiJjbnQvdXBsb2Fkcy9sb2dvcy9qb3MtYS1iYW5rLmpwZyIsIm91dHB1dEZvcm1hdCI6IiIsImVkaXRzIjp7InJlc2l6ZSI6eyJ3aWR0aCI6MTE3MH19fQ==?1606894191\"\n  },\n  {\n    \"X\": 16037,\n    \"Shop\": \"Jos A Bank\",\n    \"LABLE\": \"$25\",\n    \"Desc\": \"Jos A Bank Promo Code: $25 off\",\n    \"Code\": \"AZEY3009737\",\n    \"Souce\": \"https://www.josbank.com/\",\n    \"LOGO\": \"/cnt/uploads/logos/jos-a-bank.jpg?1606894191\",\n    \"Effective_date\": \"2022-11-22T23:29:00-08:00\",\n    \"check_date\": \"2022-12-01T11:38:03-08:00\",\n    \"Expire_date\": \"2022-12-01T11:38:03-08:00\",\n    \"img_link\": \"https://coupons.cnet.com/image/eyJrZXkiOiJjbnQvdXBsb2Fkcy9sb2dvcy9qb3MtYS1iYW5rLmpwZyIsIm91dHB1dEZvcm1hdCI6IiIsImVkaXRzIjp7InJlc2l6ZSI6eyJ3aWR0aCI6MTE3MH19fQ==?1606894191\"\n  },\n  {\n    \"X\": 16038,\n    \"Shop\": \"Jos A Bank\",\n    \"LABLE\": \"20%\",\n    \"Desc\": \"Save Big: 20% off\",\n    \"Code\": \"AYHG1113737\",\n    \"Souce\": \"https://www.josbank.com/\",\n    \"LOGO\": \"/cnt/uploads/logos/jos-a-bank.jpg?1606894191\",\n    \"Effective_date\": \"2022-11-22T23:27:00-08:00\",\n    \"check_date\": \"2022-12-01T11:37:15-08:00\",\n    \"Expire_date\": \"2022-12-01T11:37:15-08:00\",\n    \"img_link\": \"https://coupons.cnet.com/image/eyJrZXkiOiJjbnQvdXBsb2Fkcy9sb2dvcy9qb3MtYS1iYW5rLmpwZyIsIm91dHB1dEZvcm1hdCI6IiIsImVkaXRzIjp7InJlc2l6ZSI6eyJ3aWR0aCI6MTE3MH19fQ==?1606894191\"\n  },\n  {\n    \"X\": 16039,\n    \"Shop\": \"Jos A Bank\",\n    \"LABLE\": \"$39.99\",\n    \"Desc\": \"Final Sale! Get Sportshirts Now $39.99 with this Offer\",\n    \"Code\": \"Discount Displayed on Site\",\n    \"Souce\": \"https://www.josbank.com/\",\n    \"LOGO\": \"/cnt/uploads/logos/jos-a-bank.jpg?1606894191\",\n    \"Effective_date\": \"2022-09-20T06:54:00-07:00\",\n    \"Expire_date\": \"2022-11-20T23:59:59-08:00\",\n    \"img_link\": \"https://coupons.cnet.com/image/eyJrZXkiOiJjbnQvdXBsb2Fkcy9sb2dvcy9qb3MtYS1iYW5rLmpwZyIsIm91dHB1dEZvcm1hdCI6IiIsImVkaXRzIjp7InJlc2l6ZSI6eyJ3aWR0aCI6MTE3MH19fQ==?1606894191\"\n  },\n  {\n    \"X\": 16040,\n    \"Shop\": \"Jos A Bank\",\n    \"LABLE\": \"$25\",\n    \"Desc\": \"Top Coupon: $25 off Your Order\",\n    \"Code\": \"AZEY3789253\",\n    \"Souce\": \"https://www.josbank.com/\",\n    \"LOGO\": \"/cnt/uploads/logos/jos-a-bank.jpg?1606894191\",\n    \"Effective_date\": \"2022-11-05T23:10:00-07:00\",\n    \"Expire_date\": \"2022-11-11T04:59:00-08:00\",\n    \"img_link\": \"https://coupons.cnet.com/image/eyJrZXkiOiJjbnQvdXBsb2Fkcy9sb2dvcy9qb3MtYS1iYW5rLmpwZyIsIm91dHB1dEZvcm1hdCI6IiIsImVkaXRzIjp7InJlc2l6ZSI6eyJ3aWR0aCI6MTE3MH19fQ==?1606894191\"\n  },\n  {\n    \"X\": 16041,\n    \"Shop\": \"Jos A Bank\",\n    \"LABLE\": \"$99.99\",\n    \"Desc\": \"Take advantage: 1905 Chino Pants Now $99.99\",\n    \"Code\": \"Discount Displayed on Site\",\n    \"Souce\": \"https://www.josbank.com/\",\n    \"LOGO\": \"/cnt/uploads/logos/jos-a-bank.jpg?1606894191\",\n    \"Effective_date\": \"2022-09-08T16:11:00-07:00\",\n    \"Expire_date\": \"2022-11-08T23:59:59-08:00\",\n    \"img_link\": \"https://coupons.cnet.com/image/eyJrZXkiOiJjbnQvdXBsb2Fkcy9sb2dvcy9qb3MtYS1iYW5rLmpwZyIsIm91dHB1dEZvcm1hdCI6IiIsImVkaXRzIjp7InJlc2l6ZSI6eyJ3aWR0aCI6MTE3MH19fQ==?1606894191\"\n  },\n  {\n    \"X\": 16042,\n    \"Shop\": \"Jos A Bank\",\n    \"LABLE\": \"$25\",\n    \"Desc\": \"$25 off Sitewide at Jos A Bank\",\n    \"Code\": \"AZFA1010101\",\n    \"Souce\": \"https://www.josbank.com/\",\n    \"LOGO\": \"/cnt/uploads/logos/jos-a-bank.jpg?1606894191\",\n    \"Effective_date\": \"2022-10-29T00:01:00-07:00\",\n    \"check_date\": \"2022-10-15T09:30:00-07:00\",\n    \"Expire_date\": \"2022-11-05T03:59:00-07:00\",\n    \"img_link\": \"https://coupons.cnet.com/image/eyJrZXkiOiJjbnQvdXBsb2Fkcy9sb2dvcy9qb3MtYS1iYW5rLmpwZyIsIm91dHB1dEZvcm1hdCI6IiIsImVkaXRzIjp7InJlc2l6ZSI6eyJ3aWR0aCI6MTE3MH19fQ==?1606894191\"\n  },\n  {\n    \"X\": 16043,\n    \"Shop\": \"Jos A Bank\",\n    \"LABLE\": \"$25\",\n    \"Desc\": \"$25 off Your Order at Jos A Bank\",\n    \"Code\": \"AZEY3687867\",\n    \"Souce\": \"https://www.josbank.com/\",\n    \"LOGO\": \"/cnt/uploads/logos/jos-a-bank.jpg?1606894191\",\n    \"Effective_date\": \"2022-10-31T23:47:00-07:00\",\n    \"Expire_date\": \"2022-11-05T03:59:00-07:00\",\n    \"img_link\": \"https://coupons.cnet.com/image/eyJrZXkiOiJjbnQvdXBsb2Fkcy9sb2dvcy9qb3MtYS1iYW5rLmpwZyIsIm91dHB1dEZvcm1hdCI6IiIsImVkaXRzIjp7InJlc2l6ZSI6eyJ3aWR0aCI6MTE3MH19fQ==?1606894191\"\n  },\n  {\n    \"X\": 16044,\n    \"Shop\": \"Jos A Bank\",\n    \"LABLE\": \"$40\",\n    \"Desc\": \"Jos A Bank Coupon: 2 for $40 Sport Shirts\",\n    \"Code\": \"Discount Displayed on Site\",\n    \"Souce\": \"https://www.josbank.com/\",\n    \"LOGO\": \"/cnt/uploads/logos/jos-a-bank.jpg?1606894191\",\n    \"Effective_date\": \"2022-09-04T16:01:00-07:00\",\n    \"Expire_date\": \"2022-11-04T00:00:00-07:00\",\n    \"img_link\": \"https://coupons.cnet.com/image/eyJrZXkiOiJjbnQvdXBsb2Fkcy9sb2dvcy9qb3MtYS1iYW5rLmpwZyIsIm91dHB1dEZvcm1hdCI6IiIsImVkaXRzIjp7InJlc2l6ZSI6eyJ3aWR0aCI6MTE3MH19fQ==?1606894191\"\n  },\n  {\n    \"X\": 16045,\n    \"Shop\": \"Jos A Bank\",\n    \"LABLE\": \"$50\",\n    \"Desc\": \"Save at Jos A Bank with 2 for $50 Polos\",\n    \"Code\": \"Discount Displayed on Site\",\n    \"Souce\": \"https://www.josbank.com/\",\n    \"LOGO\": \"/cnt/uploads/logos/jos-a-bank.jpg?1606894191\",\n    \"Effective_date\": \"2022-09-04T16:01:00-07:00\",\n    \"check_date\": \"2022-09-18T09:21:42-07:00\",\n    \"Expire_date\": \"2022-11-04T00:00:00-07:00\",\n    \"img_link\": \"https://coupons.cnet.com/image/eyJrZXkiOiJjbnQvdXBsb2Fkcy9sb2dvcy9qb3MtYS1iYW5rLmpwZyIsIm91dHB1dEZvcm1hdCI6IiIsImVkaXRzIjp7InJlc2l6ZSI6eyJ3aWR0aCI6MTE3MH19fQ==?1606894191\"\n  },\n  {\n    \"X\": 16046,\n    \"Shop\": \"Jos A Bank\",\n    \"LABLE\": \"$35\",\n    \"Desc\": \"Seasonal Savings: Dress Shirts as low as $35\",\n    \"Code\": \"Discount Displayed on Site\",\n    \"Souce\": \"https://www.josbank.com/\",\n    \"LOGO\": \"/cnt/uploads/logos/jos-a-bank.jpg?1606894191\",\n    \"Effective_date\": \"2022-09-02T22:25:00-07:00\",\n    \"Expire_date\": \"2022-11-02T23:59:59-07:00\",\n    \"img_link\": \"https://coupons.cnet.com/image/eyJrZXkiOiJjbnQvdXBsb2Fkcy9sb2dvcy9qb3MtYS1iYW5rLmpwZyIsIm91dHB1dEZvcm1hdCI6IiIsImVkaXRzIjp7InJlc2l6ZSI6eyJ3aWR0aCI6MTE3MH19fQ==?1606894191\"\n  }\n]"]
